skbonus/__init__.py
skbonus/linear_model/__init__.py
skbonus/linear_model/_scipy_regressors.py
skbonus/linear_model/tests/__init__.py
skbonus/linear_model/tests/test__general.py
skbonus/linear_model/tests/test_imbalanced_linear_regression.py
skbonus/linear_model/tests/test_quantile_regression.py
skbonus/meta/__init__.py
skbonus/meta/_explainable_regressor.py
skbonus/meta/_zero_inflated_regressor.py
skbonus/meta/tests/__init__.py
skbonus/meta/tests/test__general.py
skbonus/metrics/__init__.py
skbonus/metrics/_regression.py
skbonus/metrics/tests/__init__.py
skbonus/metrics/tests/test_regression.py
skbonus/outlier/__init__.py
skbonus/outlier/naive.py
skbonus/outlier/tests/__init__.py
skbonus/outlier/tests/test__general.py
skbonus/pandas/__init__.py
skbonus/pandas/preprocessing.py
skbonus/pandas/time_utils.py
skbonus/pandas/tests/__init__.py
skbonus/pandas/tests/test_one_hot_encoder_with_names.py
skbonus/pandas/tests/test_time_utils.py
skbonus/preprocessing/__init__.py
skbonus/preprocessing/saturation.py
skbonus/preprocessing/time.py
skbonus/preprocessing/tests/__init__.py
skbonus/preprocessing/tests/test__general.py
skbonus/preprocessing/tests/test_time.py
skbonus/timeseries/__init__.py
skbonus/timeseries/outliers.py
skbonus/timeseries/smoothing.py
skbonus/timeseries/tests/__init__.py
skbonus/timeseries/tests/test__general.py
skbonus/timeseries/tests/test__outlier.py
scikit_bonus-0.1.12.dist-info/LICENSE.txt
scikit_bonus-0.1.12.dist-info/METADATA
scikit_bonus-0.1.12.dist-info/WHEEL
scikit_bonus-0.1.12.dist-info/top_level.txt
scikit_bonus-0.1.12.dist-info/RECORD
