Metadata-Version: 2.1
Name: scikit-bonus
Version: 0.1.12
Summary: Extending scikit-learn with various useful things.
Home-page: https://github.com/Garve/scikit-bonus
Author: Robert Kübler
Author-email: xgarve@gmail.com
License: UNKNOWN
Platform: UNKNOWN
Classifier: License :: OSI Approved :: BSD License
Classifier: Operating System :: OS Independent
Classifier: Intended Audience :: Developers
Classifier: Intended Audience :: Science/Research
Classifier: Programming Language :: Python :: 3
Classifier: Topic :: Scientific/Engineering
Classifier: Topic :: Scientific/Engineering :: Artificial Intelligence
Requires-Python: >=3.7
Requires-Dist: scikit-learn (>=0.24.0)
Requires-Dist: pandas (>=1.2.1)
Requires-Dist: numpy (>=1.18.5)
Requires-Dist: scipy (>=1.5.0)
Provides-Extra: test
Requires-Dist: flake8 (>=3.8.4) ; extra == 'test'
Requires-Dist: pytest (>=6.2.2) ; extra == 'test'
Requires-Dist: black (>=20.8b1) ; extra == 'test'
Requires-Dist: pre-commit (>=2.10.0) ; extra == 'test'
Requires-Dist: pydocstyle (>=5.1.1) ; extra == 'test'
